src/firstpkg/__init__.py
rmspkg-0.0.1.dist-info/METADATA
rmspkg-0.0.1.dist-info/WHEEL
rmspkg-0.0.1.dist-info/licenses/LICENSE
rmspkg-0.0.1.dist-info/RECORD
