Metadata-Version: 2.1
Name: RMSPKG
Version: 0.0.1
Summary: my first ever package
Author-email: Rachit Murarka <murarka.10.rachit.v@gmail.com>
License-File: LICENSE
Classifier: License :: OSI Approved :: MIT License
Classifier: Operating System :: OS Independent
Classifier: Programming Language :: Python :: 3
Requires-Python: >=3.7
